[
    {
      "_id": 1,
      "nome": "João Silva",
      "documento": 123456789,
      "telefone": 1122334455,
      "endereco": "Rua A, 123"
    },
    {
      "_id": 2,
      "nome": "Maria Santos",
      "documento": 987654321,
      "telefone": 9988776655,
      "endereco": "Avenida B, 456"
    },
    {
      "_id": 3,
      "nome": "Pedro Almeida",
      "documento": 246813579,
      "telefone": 1122334455,
      "endereco": "Rua C, 789"
    },
    {
      "_id": 4,
      "nome": "Ana Pereira",
      "documento": 135792468,
      "telefone": 5544332211,
      "endereco": "Avenida D, 987"
    },
    {
      "_id": 5,
      "nome": "Lucas Oliveira",
      "documento": 864209753,
      "telefone": 33338888,
      "endereco": "Rua E, 654"
    },
    {
      "_id": 6,
      "nome": "Julia Mendes",
      "documento": 975310864,
      "telefone": 9999888877,
      "endereco": "Avenida F, 321"
    },
    {
      "_id": 7,
      "nome": "Gabriel Fernandes",
      "documento": 528401739,
      "telefone": 1111222233,
      "endereco": "Rua G, 741"
    },
    {
      "_id": 8,
      "nome": "Mariana Costa",
      "documento": 173948205,
      "telefone": 5555777711,
      "endereco": "Avenida H, 963"
    },
    {
      "_id": 9,
      "nome": "Rafaela Santos",
      "documento": 729405183,
      "telefone": 2222444455,
      "endereco": "Rua I, 159"
    },
    {
      "_id": 10,
      "nome": "Carlos Oliveira",
      "documento": 619283746,
      "telefone": 6666111188,
      "endereco": "Avenida J, 753"
    },
    {
      "_id": 11,
      "nome": "Camila Rodrigues",
      "documento": 465738291,
      "telefone": 3333222211,
      "endereco": "Rua K, 357"
    },
    {
      "_id": 12,
      "nome": "Bruno Santos",
      "documento": 827364518,
      "telefone": 9999777755,
      "endereco": "Avenida L, 951"
    },
    {
      "_id": 13,
      "nome": "Amanda Ferreira",
      "documento": 273648591,
      "telefone": 1111222233,
      "endereco": "Rua M, 753"
    },
    {
      "_id": 14,
      "nome": "Gustavo Lima",
      "documento": 193748562,
      "telefone": 5555333344,
      "endereco": "Avenida N, 159"
    }

]